{
  "$schema": "https://json-schema.org/draft/2020-12/schema",
  "$id": "https://raw.githubusercontent.com/api-evangelist/amadeus/refs/heads/main/json-schema/hotel-ratings-error401-schema.json",
  "title": "Error401",
  "description": "Error401 schema from Hotel Ratings",
  "properties": {
    "errors": {
      "type": "array",
      "items": {
        "required": [
          "status",
          "code",
          "title"
        ],
        "properties": {
          "status": {
            "type": "integer",
            "description": "The [HTTP status code](https://www.iana.org/assignments/http-status-codes/http-status-codes.xhtml) of this response. This is present only in terminal errors which cause an unsuccessful response. In the case of multiple errors, they must all have the same status.",
            "example": 1
          },
          "code": {
            "type": "integer",
            "description": "A machine-readable error code from the Amadeus Canned Messages table, that will enable the API Consumers code to handle this type of error",
            "example": 1
          },
          "title": {
            "type": "string",
            "description": "An error title from the Canned Messages table with a 1:1 correspondence to the error code. This may be localized",
            "example": "string-value"
          },
          "detail": {
            "type": "string",
            "description": "An easy-to-read explanation specific to this occurrence of the problem. It should give the API consumer an idea of what went wrong and how to recover from it. Like the title, this field\u2019s value can be localized.",
            "example": "string-value"
          },
          "source": {
            "$ref": "#/definitions/ErrorSource"
          },
          "documentation": {
            "type": "string",
            "format": "url",
            "description": "A link to a web page or file with further documentation to help the API consumer resolve this error",
            "example": "https://example.com/resource"
          }
        }
      }
    }
  },
  "required": [
    "errors"
  ],
  "example": {
    "errors": [
      {
        "status": 401,
        "code": 20,
        "title": "RESTRICTED",
        "detail": "Query unauthorized"
      }
    ]
  },
  "type": "object"
}